[
	{
		"_id" : "jremillard-massgis",
		"count" : 262718
	},
	{
		"_id" : "greggerm",
		"count" : 191072
	},
	{
		"_id" : "woodpeck_fixbot",
		"count" : 118087
	},
	{
		"_id" : "azsr",
		"count" : 30491
	},
	{
		"_id" : "Zirnch",
		"count" : 29510
	},
	{
		"_id" : "MassGIS Import",
		"count" : 26257
	},
	{
		"_id" : "Roman Guy",
		"count" : 10469
	},
	{
		"_id" : "bot-mode",
		"count" : 9367
	},
	{
		"_id" : "John Wrenn",
		"count" : 9304
	},
	{
		"_id" : "wambag",
		"count" : 8205
	},
	{
		"_id" : "Alex KG Ellis",
		"count" : 7742
	},
	{
		"_id" : "jerryam",
		"count" : 7101
	},
	{
		"_id" : "OceanVortex",
		"count" : 6472
	},
	{
		"_id" : "maxerickson",
		"count" : 6285
	},
	{
		"_id" : "EmilyPPP",
		"count" : 4703
	},
	{
		"_id" : "miluethi",
		"count" : 4637
	},
	{
		"_id" : "Di Splainame",
		"count" : 4487
	},
	{
		"_id" : "42429",
		"count" : 4473
	},
	{
		"_id" : "crschmidt",
		"count" : 4390
	},
	{
		"_id" : "morganwahl",
		"count" : 3850
	},
	{
		"_id" : "NE2",
		"count" : 3840
	},
	{
		"_id" : "Alan Bragg",
		"count" : 3351
	},
	{
		"_id" : "Peter Dobratz",
		"count" : 3331
	},
	{
		"_id" : "TIGERcnl",
		"count" : 3069
	},
	{
		"_id" : "Leo22",
		"count" : 2746
	},
	{
		"_id" : "underorbit",
		"count" : 2287
	},
	{
		"_id" : "ZeLonewolf",
		"count" : 1892
	},
	{
		"_id" : "Outlier73",
		"count" : 1719
	},
	{
		"_id" : "JasonWoof",
		"count" : 1520
	},
	{
		"_id" : "choess",
		"count" : 1486
	},
	{
		"_id" : "jamacho",
		"count" : 1282
	},
	{
		"_id" : "Durango",
		"count" : 1219
	},
	{
		"_id" : "Werewombat",
		"count" : 1210
	},
	{
		"_id" : "tebiggs",
		"count" : 1179
	},
	{
		"_id" : "KindredCoda",
		"count" : 1062
	},
	{
		"_id" : "swimdb",
		"count" : 1016
	},
	{
		"_id" : "OMMB",
		"count" : 1005
	},
	{
		"_id" : "gdt",
		"count" : 914
	},
	{
		"_id" : "ftavares87",
		"count" : 914
	},
	{
		"_id" : "Latze",
		"count" : 892
	},
	{
		"_id" : "mahahahaneapneap",
		"count" : 854
	},
	{
		"_id" : "Spinosaursus",
		"count" : 796
	},
	{
		"_id" : "tbhartman",
		"count" : 792
	},
	{
		"_id" : "DaveHansenTiger",
		"count" : 728
	},
	{
		"_id" : "cybhunter",
		"count" : 715
	},
	{
		"_id" : "Ken Horn",
		"count" : 708
	},
	{
		"_id" : "blahedo",
		"count" : 688
	},
	{
		"_id" : "siranachronist",
		"count" : 637
	},
	{
		"_id" : "GeoStudent",
		"count" : 628
	},
	{
		"_id" : "JessAk71",
		"count" : 616
	},
	{
		"_id" : "brianjmcguirk",
		"count" : 614
	},
	{
		"_id" : "osm2xp",
		"count" : 561
	},
	{
		"_id" : "RoadGeek_MD99",
		"count" : 557
	},
	{
		"_id" : "Luis36995",
		"count" : 554
	},
	{
		"_id" : "iandees",
		"count" : 536
	},
	{
		"_id" : "Coolc6401",
		"count" : 531
	},
	{
		"_id" : "LinusA",
		"count" : 485
	},
	{
		"_id" : "Downy_288",
		"count" : 450
	},
	{
		"_id" : "oldtopos",
		"count" : 447
	},
	{
		"_id" : "user_5359",
		"count" : 443
	},
	{
		"_id" : "Yoshinion",
		"count" : 440
	},
	{
		"_id" : "eminence",
		"count" : 439
	},
	{
		"_id" : "Ahlzen",
		"count" : 438
	},
	{
		"_id" : "mcaldwell_1372",
		"count" : 433
	},
	{
		"_id" : "andrewbenedictwallace",
		"count" : 429
	},
	{
		"_id" : "Shadow187",
		"count" : 388
	},
	{
		"_id" : "oba510",
		"count" : 387
	},
	{
		"_id" : "Windows98",
		"count" : 378
	},
	{
		"_id" : "OldShamanizer",
		"count" : 372
	},
	{
		"_id" : "DavidZ",
		"count" : 372
	},
	{
		"_id" : "sfn",
		"count" : 360
	},
	{
		"_id" : "samely",
		"count" : 350
	},
	{
		"_id" : "martini_p",
		"count" : 346
	},
	{
		"_id" : "SK53",
		"count" : 344
	},
	{
		"_id" : "The Inning Club",
		"count" : 331
	},
	{
		"_id" : "cjudge05",
		"count" : 308
	},
	{
		"_id" : "mvexel",
		"count" : 292
	},
	{
		"_id" : "Downy288",
		"count" : 292
	},
	{
		"_id" : "dannykath",
		"count" : 276
	},
	{
		"_id" : "RyanP724",
		"count" : 274
	},
	{
		"_id" : "Jason78",
		"count" : 271
	},
	{
		"_id" : "pyram",
		"count" : 251
	},
	{
		"_id" : "openstreeteditor345789",
		"count" : 244
	},
	{
		"_id" : "calfarome",
		"count" : 241
	},
	{
		"_id" : "maptastical",
		"count" : 240
	},
	{
		"_id" : "blueteam",
		"count" : 237
	},
	{
		"_id" : "rad1ance",
		"count" : 234
	},
	{
		"_id" : "Walleye2013",
		"count" : 224
	},
	{
		"_id" : "Jumpingjackz",
		"count" : 207
	},
	{
		"_id" : "swhite3137",
		"count" : 207
	},
	{
		"_id" : "JJayzX",
		"count" : 204
	},
	{
		"_id" : "RichRico",
		"count" : 196
	},
	{
		"_id" : "JJab",
		"count" : 193
	},
	{
		"_id" : "ed_borges91",
		"count" : 191
	},
	{
		"_id" : "KristenK",
		"count" : 190
	},
	{
		"_id" : "BMS_FLL_2013",
		"count" : 190
	},
	{
		"_id" : "chehrlic",
		"count" : 186
	},
	{
		"_id" : "Steven Deeds",
		"count" : 183
	},
	{
		"_id" : "Maskulinum",
		"count" : 180
	},
	{
		"_id" : "amillar",
		"count" : 180
	},
	{
		"_id" : "pratikyadav",
		"count" : 171
	},
	{
		"_id" : "PHerison",
		"count" : 171
	},
	{
		"_id" : "ramyaragupathy",
		"count" : 170
	},
	{
		"_id" : "B-rock",
		"count" : 167
	},
	{
		"_id" : "debutterfly",
		"count" : 163
	},
	{
		"_id" : "Bryan Sabbag",
		"count" : 162
	},
	{
		"_id" : "commanderbond88",
		"count" : 161
	},
	{
		"_id" : "MeatballZ28",
		"count" : 159
	},
	{
		"_id" : "ediyes",
		"count" : 157
	},
	{
		"_id" : "EdSS",
		"count" : 156
	},
	{
		"_id" : "thetornado76",
		"count" : 151
	},
	{
		"_id" : "daganzdaanda",
		"count" : 150
	},
	{
		"_id" : "Cameron515",
		"count" : 148
	},
	{
		"_id" : "Edward",
		"count" : 148
	},
	{
		"_id" : "Wraithx21",
		"count" : 148
	},
	{
		"_id" : "karitotp",
		"count" : 144
	},
	{
		"_id" : "Bill Ricker",
		"count" : 142
	},
	{
		"_id" : "Parcanman",
		"count" : 139
	},
	{
		"_id" : "Odion",
		"count" : 139
	},
	{
		"_id" : "goldenmeanie",
		"count" : 136
	},
	{
		"_id" : "hofoen",
		"count" : 132
	},
	{
		"_id" : "andrewpmk",
		"count" : 131
	},
	{
		"_id" : "steverumizen",
		"count" : 131
	},
	{
		"_id" : "Skywave",
		"count" : 128
	},
	{
		"_id" : "MattyCiii",
		"count" : 127
	},
	{
		"_id" : "em21701",
		"count" : 125
	},
	{
		"_id" : "Claumires",
		"count" : 120
	},
	{
		"_id" : "RD1",
		"count" : 118
	},
	{
		"_id" : "stevea",
		"count" : 118
	},
	{
		"_id" : "abel801",
		"count" : 117
	},
	{
		"_id" : "Geogast",
		"count" : 116
	},
	{
		"_id" : "matty339",
		"count" : 110
	},
	{
		"_id" : "Ilya Radchenko",
		"count" : 110
	},
	{
		"_id" : "viana",
		"count" : 110
	},
	{
		"_id" : "cliffcake",
		"count" : 110
	},
	{
		"_id" : "sctrojan79",
		"count" : 109
	},
	{
		"_id" : "Geoff Meek",
		"count" : 108
	},
	{
		"_id" : "werner2101",
		"count" : 107
	},
	{
		"_id" : "Jothirnadh",
		"count" : 104
	},
	{
		"_id" : "rubyk",
		"count" : 99
	},
	{
		"_id" : "zeromap",
		"count" : 99
	},
	{
		"_id" : "Cato_d_Ae",
		"count" : 99
	},
	{
		"_id" : "joemadeus",
		"count" : 98
	},
	{
		"_id" : "George888",
		"count" : 97
	},
	{
		"_id" : "davidearl",
		"count" : 92
	},
	{
		"_id" : "sebastic",
		"count" : 90
	},
	{
		"_id" : "Luccnoir",
		"count" : 90
	},
	{
		"_id" : "tyos",
		"count" : 90
	},
	{
		"_id" : "leip67",
		"count" : 90
	},
	{
		"_id" : "jmhobson",
		"count" : 88
	},
	{
		"_id" : "dominastrum",
		"count" : 84
	},
	{
		"_id" : "Tom Morris",
		"count" : 84
	},
	{
		"_id" : "stangoodman",
		"count" : 82
	},
	{
		"_id" : "Romira Monteiro",
		"count" : 82
	},
	{
		"_id" : "udairman71",
		"count" : 80
	},
	{
		"_id" : "mregan",
		"count" : 80
	},
	{
		"_id" : "teodorab_telenav",
		"count" : 79
	},
	{
		"_id" : "nkhall",
		"count" : 77
	},
	{
		"_id" : "DougPeterson",
		"count" : 77
	},
	{
		"_id" : "CSheehy",
		"count" : 75
	},
	{
		"_id" : "MikeN",
		"count" : 74
	},
	{
		"_id" : "Jonathan ZHAO",
		"count" : 71
	},
	{
		"_id" : "daemonkity",
		"count" : 70
	},
	{
		"_id" : "hollybogo",
		"count" : 68
	},
	{
		"_id" : "MGH",
		"count" : 67
	},
	{
		"_id" : "Wubby",
		"count" : 66
	},
	{
		"_id" : "njaard",
		"count" : 65
	},
	{
		"_id" : "bbmiller",
		"count" : 60
	},
	{
		"_id" : "9spades",
		"count" : 60
	},
	{
		"_id" : "florinbadita_telenav",
		"count" : 59
	},
	{
		"_id" : "andygol",
		"count" : 59
	},
	{
		"_id" : "CloCkWeRX",
		"count" : 57
	},
	{
		"_id" : "johnsdixon",
		"count" : 57
	},
	{
		"_id" : "Maarten Deen",
		"count" : 56
	},
	{
		"_id" : "youngbasedallah",
		"count" : 54
	},
	{
		"_id" : "KevinInFoxpoint",
		"count" : 53
	},
	{
		"_id" : "chdr",
		"count" : 53
	},
	{
		"_id" : "ChrisZontine",
		"count" : 52
	},
	{
		"_id" : "bostonniles",
		"count" : 52
	},
	{
		"_id" : "kd1oq",
		"count" : 51
	},
	{
		"_id" : "cycleedit",
		"count" : 50
	},
	{
		"_id" : "jwass",
		"count" : 50
	},
	{
		"_id" : "Iqhra",
		"count" : 47
	},
	{
		"_id" : "rickmastfan67",
		"count" : 47
	},
	{
		"_id" : "Prof Eric Cameron",
		"count" : 45
	},
	{
		"_id" : "bezek",
		"count" : 44
	},
	{
		"_id" : "Edward Munch",
		"count" : 43
	},
	{
		"_id" : "dmgroom_ct",
		"count" : 43
	},
	{
		"_id" : "cpendergast5727",
		"count" : 43
	},
	{
		"_id" : "cgsk8blind",
		"count" : 42
	},
	{
		"_id" : "mdistaolo",
		"count" : 41
	},
	{
		"_id" : "shredmo",
		"count" : 41
	},
	{
		"_id" : "dalmond",
		"count" : 40
	},
	{
		"_id" : "jpx_",
		"count" : 40
	},
	{
		"_id" : "ruthmaben",
		"count" : 40
	},
	{
		"_id" : "Seth Dixon",
		"count" : 40
	},
	{
		"_id" : "jremillard",
		"count" : 40
	},
	{
		"_id" : "Nathanael Neveux",
		"count" : 39
	},
	{
		"_id" : "Munchabunch",
		"count" : 38
	},
	{
		"_id" : "RIsailor",
		"count" : 38
	},
	{
		"_id" : "massDOT",
		"count" : 37
	},
	{
		"_id" : "Vlad",
		"count" : 37
	},
	{
		"_id" : "Szeth",
		"count" : 36
	},
	{
		"_id" : "pdunn",
		"count" : 36
	},
	{
		"_id" : "ceyockey",
		"count" : 36
	},
	{
		"_id" : "parice",
		"count" : 36
	},
	{
		"_id" : "esterichia",
		"count" : 35
	},
	{
		"_id" : "Lindsayrose1227",
		"count" : 35
	},
	{
		"_id" : "Chelsea Carney",
		"count" : 35
	},
	{
		"_id" : "Joshua Mason",
		"count" : 34
	},
	{
		"_id" : "ToeBee",
		"count" : 34
	},
	{
		"_id" : "GoWestTravel",
		"count" : 34
	},
	{
		"_id" : "BigE56",
		"count" : 34
	},
	{
		"_id" : "NE3",
		"count" : 33
	},
	{
		"_id" : "I Am Not Telling You My Name",
		"count" : 33
	},
	{
		"_id" : "almiki",
		"count" : 32
	},
	{
		"_id" : "rolandg",
		"count" : 32
	},
	{
		"_id" : "nikhilprabhakar",
		"count" : 31
	},
	{
		"_id" : "yudenis de jesus",
		"count" : 31
	},
	{
		"_id" : "ppba",
		"count" : 30
	},
	{
		"_id" : "201geog14",
		"count" : 29
	},
	{
		"_id" : "mikeauclair",
		"count" : 29
	},
	{
		"_id" : "Andrew Matheny",
		"count" : 28
	},
	{
		"_id" : "1024mar35",
		"count" : 28
	},
	{
		"_id" : "LXT",
		"count" : 28
	},
	{
		"_id" : "benbrig",
		"count" : 26
	},
	{
		"_id" : "TheNice",
		"count" : 26
	},
	{
		"_id" : "jpaznio",
		"count" : 26
	},
	{
		"_id" : "adamos",
		"count" : 26
	},
	{
		"_id" : "Channy Ngin",
		"count" : 26
	},
	{
		"_id" : "Sploolordcam",
		"count" : 25
	},
	{
		"_id" : "tpawlitschek",
		"count" : 25
	},
	{
		"_id" : "ipodolsk",
		"count" : 25
	},
	{
		"_id" : "ioanam_telenav",
		"count" : 25
	},
	{
		"_id" : "epottiermbta",
		"count" : 24
	},
	{
		"_id" : "yurasi",
		"count" : 24
	},
	{
		"_id" : "cbuijs",
		"count" : 24
	},
	{
		"_id" : "hazmat696969",
		"count" : 24
	},
	{
		"_id" : "Lauren Duvall",
		"count" : 24
	},
	{
		"_id" : "KenniaC",
		"count" : 23
	},
	{
		"_id" : "uboot",
		"count" : 23
	},
	{
		"_id" : "NateOMatic",
		"count" : 23
	},
	{
		"_id" : "Monica Brandeis",
		"count" : 22
	},
	{
		"_id" : "ACE|Tony",
		"count" : 22
	},
	{
		"_id" : "OSMF Redaction Account",
		"count" : 22
	},
	{
		"_id" : "gmccauley_4904",
		"count" : 22
	},
	{
		"_id" : "DanielRoach",
		"count" : 21
	},
	{
		"_id" : "jokeefe",
		"count" : 21
	},
	{
		"_id" : "Peter14",
		"count" : 20
	},
	{
		"_id" : "vkungys",
		"count" : 20
	},
	{
		"_id" : "nyuriks",
		"count" : 20
	},
	{
		"_id" : "Ailish",
		"count" : 20
	},
	{
		"_id" : "garykg2",
		"count" : 20
	},
	{
		"_id" : "jonesydesign",
		"count" : 19
	},
	{
		"_id" : "TornadoShepherd",
		"count" : 19
	},
	{
		"_id" : "Jack Dougherty",
		"count" : 18
	},
	{
		"_id" : "homeslice60148",
		"count" : 18
	},
	{
		"_id" : "Kellye-Coast",
		"count" : 18
	},
	{
		"_id" : "danbjoseph",
		"count" : 18
	},
	{
		"_id" : "msmoritz",
		"count" : 18
	},
	{
		"_id" : "woodpeck_repair",
		"count" : 18
	},
	{
		"_id" : "acas",
		"count" : 18
	},
	{
		"_id" : "FloppusMaximus",
		"count" : 17
	},
	{
		"_id" : "wolfgang8741",
		"count" : 17
	},
	{
		"_id" : "Timothy Smith",
		"count" : 17
	},
	{
		"_id" : "Nayt44",
		"count" : 17
	},
	{
		"_id" : "Batman Says 5",
		"count" : 17
	},
	{
		"_id" : "scoopoo",
		"count" : 16
	},
	{
		"_id" : "Kahree Silva",
		"count" : 16
	},
	{
		"_id" : "JeffM8",
		"count" : 16
	},
	{
		"_id" : "PlaneMad",
		"count" : 16
	},
	{
		"_id" : "neveroddoreven",
		"count" : 16
	},
	{
		"_id" : "PatriciaEkpo",
		"count" : 16
	},
	{
		"_id" : "eroncanc",
		"count" : 16
	},
	{
		"_id" : "enokp",
		"count" : 16
	},
	{
		"_id" : "tehcraz",
		"count" : 16
	},
	{
		"_id" : "Sophie Chien",
		"count" : 15
	},
	{
		"_id" : "Steve",
		"count" : 15
	},
	{
		"_id" : "nessa2514",
		"count" : 15
	},
	{
		"_id" : "riclab15",
		"count" : 15
	},
	{
		"_id" : "Hobgoblin",
		"count" : 15
	},
	{
		"_id" : "kKaee33",
		"count" : 14
	},
	{
		"_id" : "dylancahir",
		"count" : 14
	},
	{
		"_id" : "piligab",
		"count" : 14
	},
	{
		"_id" : "ranjithjoy",
		"count" : 14
	},
	{
		"_id" : "BeKri",
		"count" : 14
	},
	{
		"_id" : "DKNOTT",
		"count" : 14
	},
	{
		"_id" : "mmatook_8950",
		"count" : 14
	},
	{
		"_id" : "Jordan72",
		"count" : 14
	},
	{
		"_id" : "SK-808",
		"count" : 13
	},
	{
		"_id" : "BKingDC",
		"count" : 13
	},
	{
		"_id" : "ridixcr",
		"count" : 13
	},
	{
		"_id" : "201Geog17",
		"count" : 13
	},
	{
		"_id" : "mapgive15st",
		"count" : 13
	},
	{
		"_id" : "Pnrrth",
		"count" : 12
	},
	{
		"_id" : "kerisilva",
		"count" : 12
	},
	{
		"_id" : "Maggie15",
		"count" : 12
	},
	{
		"_id" : "Sarr_Cat",
		"count" : 12
	},
	{
		"_id" : "Parker544",
		"count" : 12
	},
	{
		"_id" : "crystalwalrein",
		"count" : 12
	},
	{
		"_id" : "BBoucek",
		"count" : 12
	},
	{
		"_id" : "RILockGuy",
		"count" : 11
	},
	{
		"_id" : "retrev",
		"count" : 11
	},
	{
		"_id" : "Stephen214",
		"count" : 11
	},
	{
		"_id" : "amishius",
		"count" : 11
	},
	{
		"_id" : "nammala",
		"count" : 11
	},
	{
		"_id" : "NayanataraM",
		"count" : 11
	},
	{
		"_id" : "201Geog24",
		"count" : 11
	},
	{
		"_id" : "vademecum",
		"count" : 11
	},
	{
		"_id" : "upendrakarukonda",
		"count" : 10
	},
	{
		"_id" : "Cat Soup",
		"count" : 10
	},
	{
		"_id" : "widalys_garcia",
		"count" : 10
	},
	{
		"_id" : "AMoto",
		"count" : 10
	},
	{
		"_id" : "tnPerona",
		"count" : 10
	},
	{
		"_id" : "Sunny He",
		"count" : 10
	},
	{
		"_id" : "Steve Rodkey",
		"count" : 10
	},
	{
		"_id" : "TheDutchMan13",
		"count" : 10
	},
	{
		"_id" : "dbpatterson",
		"count" : 10
	},
	{
		"_id" : "ddosreis",
		"count" : 10
	},
	{
		"_id" : "pavlina88",
		"count" : 10
	},
	{
		"_id" : "Constable",
		"count" : 10
	},
	{
		"_id" : "basshunter401",
		"count" : 10
	},
	{
		"_id" : "aquablib",
		"count" : 10
	},
	{
		"_id" : "RhodeMaps",
		"count" : 10
	},
	{
		"_id" : "ezr2",
		"count" : 10
	},
	{
		"_id" : "darsenault",
		"count" : 9
	},
	{
		"_id" : "Iowa Kid",
		"count" : 9
	},
	{
		"_id" : "Zandlopertje",
		"count" : 9
	},
	{
		"_id" : "j3d",
		"count" : 9
	},
	{
		"_id" : "julingts",
		"count" : 9
	},
	{
		"_id" : "TomHynes",
		"count" : 9
	},
	{
		"_id" : "sadam",
		"count" : 9
	},
	{
		"_id" : "wheelmap_visitor",
		"count" : 9
	},
	{
		"_id" : "nairon",
		"count" : 9
	},
	{
		"_id" : "mork the delayer",
		"count" : 9
	},
	{
		"_id" : "chaseboni",
		"count" : 9
	},
	{
		"_id" : "mcccliv",
		"count" : 8
	},
	{
		"_id" : "SomeoneElse_Revert",
		"count" : 8
	},
	{
		"_id" : "srividya_c",
		"count" : 8
	},
	{
		"_id" : "omillard",
		"count" : 8
	},
	{
		"_id" : "Tressa Cannata",
		"count" : 8
	},
	{
		"_id" : "Keyyek",
		"count" : 8
	},
	{
		"_id" : "askewchan",
		"count" : 8
	},
	{
		"_id" : "aarond9",
		"count" : 8
	},
	{
		"_id" : "msmisha",
		"count" : 8
	},
	{
		"_id" : "Fa7C0N",
		"count" : 8
	},
	{
		"_id" : "Eric Fischer",
		"count" : 8
	},
	{
		"_id" : "looshious",
		"count" : 8
	},
	{
		"_id" : "25or6to4",
		"count" : 8
	},
	{
		"_id" : "Kannafoot",
		"count" : 8
	},
	{
		"_id" : "julesreid",
		"count" : 7
	},
	{
		"_id" : "oormilavinod",
		"count" : 7
	},
	{
		"_id" : "ninjaslayer461",
		"count" : 7
	},
	{
		"_id" : "xybot",
		"count" : 7
	},
	{
		"_id" : "CapitalGoodFund",
		"count" : 7
	},
	{
		"_id" : "tombrady",
		"count" : 7
	},
	{
		"_id" : "dchiles",
		"count" : 7
	},
	{
		"_id" : "maxolasersquad",
		"count" : 7
	},
	{
		"_id" : "kre3d",
		"count" : 7
	},
	{
		"_id" : "Imp_GL",
		"count" : 7
	},
	{
		"_id" : "Alexander Roalter",
		"count" : 7
	},
	{
		"_id" : "torapa",
		"count" : 7
	},
	{
		"_id" : "cspanring",
		"count" : 7
	},
	{
		"_id" : "jumbanho",
		"count" : 7
	},
	{
		"_id" : "ashleyannmathew",
		"count" : 6
	},
	{
		"_id" : "compdude",
		"count" : 6
	},
	{
		"_id" : "huldsfred",
		"count" : 6
	},
	{
		"_id" : "magalissantana",
		"count" : 6
	},
	{
		"_id" : "Vbob",
		"count" : 6
	},
	{
		"_id" : "Blanca Mancilla",
		"count" : 6
	},
	{
		"_id" : "kickstand",
		"count" : 6
	},
	{
		"_id" : "rayro",
		"count" : 6
	},
	{
		"_id" : "kisaa",
		"count" : 6
	},
	{
		"_id" : "mike140",
		"count" : 6
	},
	{
		"_id" : "HAKEEM ETORIA",
		"count" : 6
	},
	{
		"_id" : "ashmanmedia",
		"count" : 6
	},
	{
		"_id" : "klusark",
		"count" : 6
	},
	{
		"_id" : "Mike Augustus",
		"count" : 6
	},
	{
		"_id" : "Kateg123",
		"count" : 6
	},
	{
		"_id" : "Kurly",
		"count" : 5
	},
	{
		"_id" : "Mac05",
		"count" : 5
	},
	{
		"_id" : "DataMedics",
		"count" : 5
	},
	{
		"_id" : "brogo",
		"count" : 5
	},
	{
		"_id" : "hno2",
		"count" : 5
	},
	{
		"_id" : "MilaZ",
		"count" : 5
	},
	{
		"_id" : "manings",
		"count" : 5
	},
	{
		"_id" : "Ted Mielczarek (borders upload)",
		"count" : 5
	},
	{
		"_id" : "OMapper",
		"count" : 5
	},
	{
		"_id" : "Chetan_Gowda",
		"count" : 5
	},
	{
		"_id" : "manoharuss",
		"count" : 5
	},
	{
		"_id" : "matthieun",
		"count" : 5
	},
	{
		"_id" : "RaquelFish09",
		"count" : 5
	},
	{
		"_id" : "oco50",
		"count" : 5
	},
	{
		"_id" : "Jake Strine",
		"count" : 5
	},
	{
		"_id" : "woodpeck",
		"count" : 5
	},
	{
		"_id" : "MrMucox",
		"count" : 5
	},
	{
		"_id" : "1248",
		"count" : 5
	},
	{
		"_id" : "gabis_telenav",
		"count" : 5
	},
	{
		"_id" : "bhavana naga",
		"count" : 5
	},
	{
		"_id" : "JonathanMG",
		"count" : 5
	},
	{
		"_id" : "ke9tv",
		"count" : 4
	},
	{
		"_id" : "Gludoo",
		"count" : 4
	},
	{
		"_id" : "Tatum",
		"count" : 4
	},
	{
		"_id" : "Syl",
		"count" : 4
	},
	{
		"_id" : "SmolderinBob",
		"count" : 4
	},
	{
		"_id" : "tod",
		"count" : 4
	},
	{
		"_id" : "FMFT",
		"count" : 4
	},
	{
		"_id" : "Margori123",
		"count" : 4
	},
	{
		"_id" : "EvanMula",
		"count" : 4
	},
	{
		"_id" : "Andreas Kloeckner",
		"count" : 4
	},
	{
		"_id" : "The Big O Face",
		"count" : 4
	},
	{
		"_id" : "ibrahimeden",
		"count" : 4
	},
	{
		"_id" : "Rellec",
		"count" : 4
	},
	{
		"_id" : "hfyu",
		"count" : 4
	},
	{
		"_id" : "RetiredInNH",
		"count" : 4
	},
	{
		"_id" : "HDHooper",
		"count" : 4
	},
	{
		"_id" : "fidcastro",
		"count" : 4
	},
	{
		"_id" : "rjhale1971",
		"count" : 4
	},
	{
		"_id" : "Emmaxi",
		"count" : 4
	},
	{
		"_id" : "Bhargav Panth",
		"count" : 4
	},
	{
		"_id" : "Walter Schlögl",
		"count" : 4
	},
	{
		"_id" : "ALE!",
		"count" : 3
	},
	{
		"_id" : "NickBolten",
		"count" : 3
	},
	{
		"_id" : "snickerdoodles",
		"count" : 3
	},
	{
		"_id" : "chaanakya",
		"count" : 3
	},
	{
		"_id" : "Matthew Goyette",
		"count" : 3
	},
	{
		"_id" : "TeresaPeteti",
		"count" : 3
	},
	{
		"_id" : "rza31",
		"count" : 3
	},
	{
		"_id" : "mateov",
		"count" : 3
	},
	{
		"_id" : "RJFerret",
		"count" : 3
	},
	{
		"_id" : "abdawson",
		"count" : 3
	},
	{
		"_id" : "Paul Gott",
		"count" : 3
	},
	{
		"_id" : "theid",
		"count" : 3
	},
	{
		"_id" : "Jaiy",
		"count" : 3
	},
	{
		"_id" : "rdol1994",
		"count" : 3
	},
	{
		"_id" : "KayRob15",
		"count" : 3
	},
	{
		"_id" : "Jim_SpeedLine",
		"count" : 3
	},
	{
		"_id" : "breic",
		"count" : 3
	},
	{
		"_id" : "pruqieoty",
		"count" : 3
	},
	{
		"_id" : "TorCguy",
		"count" : 3
	},
	{
		"_id" : "Omnific",
		"count" : 3
	},
	{
		"_id" : "Sherief",
		"count" : 3
	},
	{
		"_id" : "williamfrench4",
		"count" : 3
	},
	{
		"_id" : "Aleks-Berlin",
		"count" : 3
	},
	{
		"_id" : "Malmis",
		"count" : 3
	},
	{
		"_id" : "Arvid Tomayko-Peters",
		"count" : 3
	},
	{
		"_id" : "JBrocklesby",
		"count" : 2
	},
	{
		"_id" : "erjiang",
		"count" : 2
	},
	{
		"_id" : "carob",
		"count" : 2
	},
	{
		"_id" : "ashearer",
		"count" : 2
	},
	{
		"_id" : "mrengy",
		"count" : 2
	},
	{
		"_id" : "SP!KE",
		"count" : 2
	},
	{
		"_id" : "Joseph Bollhofer",
		"count" : 2
	},
	{
		"_id" : "revent",
		"count" : 2
	},
	{
		"_id" : "eugenebata",
		"count" : 2
	},
	{
		"_id" : "IAmZePiplup",
		"count" : 2
	},
	{
		"_id" : "FrJakob",
		"count" : 2
	},
	{
		"_id" : "Duncan Mac",
		"count" : 2
	},
	{
		"_id" : "DeividasG",
		"count" : 2
	},
	{
		"_id" : "Gone",
		"count" : 2
	},
	{
		"_id" : "SophoM",
		"count" : 2
	},
	{
		"_id" : "methowmade",
		"count" : 2
	},
	{
		"_id" : "allyeatworld7",
		"count" : 2
	},
	{
		"_id" : "Eric958",
		"count" : 2
	},
	{
		"_id" : "labarna",
		"count" : 2
	},
	{
		"_id" : "kaiserhase",
		"count" : 2
	},
	{
		"_id" : "MaverickD",
		"count" : 2
	},
	{
		"_id" : "mclaess",
		"count" : 2
	},
	{
		"_id" : "Rick StP",
		"count" : 2
	},
	{
		"_id" : "Rps333",
		"count" : 2
	},
	{
		"_id" : "nsub1",
		"count" : 2
	},
	{
		"_id" : "fx99",
		"count" : 2
	},
	{
		"_id" : "201geog27",
		"count" : 2
	},
	{
		"_id" : "bobfer",
		"count" : 2
	},
	{
		"_id" : "grossing",
		"count" : 2
	},
	{
		"_id" : "AndiG88",
		"count" : 2
	},
	{
		"_id" : "BicycleCommuter",
		"count" : 2
	},
	{
		"_id" : "cgu66",
		"count" : 2
	},
	{
		"_id" : "zardofoz",
		"count" : 2
	},
	{
		"_id" : "jasonjayr",
		"count" : 2
	},
	{
		"_id" : "h4ck3rm1k3",
		"count" : 2
	},
	{
		"_id" : "mapsinE3",
		"count" : 2
	},
	{
		"_id" : "Josef73",
		"count" : 2
	},
	{
		"_id" : "Cycleboy99",
		"count" : 2
	},
	{
		"_id" : "cheezeberger",
		"count" : 2
	},
	{
		"_id" : "nm7s9",
		"count" : 2
	},
	{
		"_id" : "qfnelson",
		"count" : 2
	},
	{
		"_id" : "Jpriola",
		"count" : 2
	},
	{
		"_id" : "mrw6060",
		"count" : 2
	},
	{
		"_id" : "SNECS",
		"count" : 2
	},
	{
		"_id" : "Theodin",
		"count" : 2
	},
	{
		"_id" : "sigmatron",
		"count" : 2
	},
	{
		"_id" : "elbatrop",
		"count" : 2
	},
	{
		"_id" : "bdiscoe",
		"count" : 1
	},
	{
		"_id" : "venkanna37",
		"count" : 1
	},
	{
		"_id" : "TDR3iW",
		"count" : 1
	},
	{
		"_id" : "adjuva",
		"count" : 1
	},
	{
		"_id" : "MKnight",
		"count" : 1
	},
	{
		"_id" : "Harry Bock",
		"count" : 1
	},
	{
		"_id" : "riordabr",
		"count" : 1
	},
	{
		"_id" : "uk1967",
		"count" : 1
	},
	{
		"_id" : "Nicole Kutz",
		"count" : 1
	},
	{
		"_id" : "maggot27",
		"count" : 1
	},
	{
		"_id" : "cdavila",
		"count" : 1
	},
	{
		"_id" : "mcgelb",
		"count" : 1
	},
	{
		"_id" : "ScottSorensen",
		"count" : 1
	},
	{
		"_id" : "dr ingrid",
		"count" : 1
	},
	{
		"_id" : "t-i",
		"count" : 1
	},
	{
		"_id" : "KathrynGeog201",
		"count" : 1
	},
	{
		"_id" : "dufekin",
		"count" : 1
	},
	{
		"_id" : "Thomas Riley",
		"count" : 1
	},
	{
		"_id" : "Tony Cannistra",
		"count" : 1
	},
	{
		"_id" : "ChrissW-R1",
		"count" : 1
	},
	{
		"_id" : "AzizBass",
		"count" : 1
	},
	{
		"_id" : "Caleb_L",
		"count" : 1
	},
	{
		"_id" : "jstring",
		"count" : 1
	},
	{
		"_id" : "map93",
		"count" : 1
	},
	{
		"_id" : "caseytattoori",
		"count" : 1
	},
	{
		"_id" : "GerdP",
		"count" : 1
	},
	{
		"_id" : "thecuriouschild",
		"count" : 1
	},
	{
		"_id" : "wehaulitinc",
		"count" : 1
	},
	{
		"_id" : "ponaugmarina",
		"count" : 1
	},
	{
		"_id" : "Bman",
		"count" : 1
	},
	{
		"_id" : "callum",
		"count" : 1
	},
	{
		"_id" : "Aaron Hertzer",
		"count" : 1
	},
	{
		"_id" : "kinefuchi",
		"count" : 1
	},
	{
		"_id" : "Mashin",
		"count" : 1
	},
	{
		"_id" : "kaona19",
		"count" : 1
	},
	{
		"_id" : "mfengbristol",
		"count" : 1
	},
	{
		"_id" : "Dero Bike Racks",
		"count" : 1
	},
	{
		"_id" : "maloneri",
		"count" : 1
	},
	{
		"_id" : "MCM7",
		"count" : 1
	},
	{
		"_id" : "bfm64",
		"count" : 1
	},
	{
		"_id" : "Edwin-D",
		"count" : 1
	},
	{
		"_id" : "Anchor",
		"count" : 1
	},
	{
		"_id" : "Samuel Hadden",
		"count" : 1
	},
	{
		"_id" : "L Gloss",
		"count" : 1
	},
	{
		"_id" : "srainwater",
		"count" : 1
	},
	{
		"_id" : "YamaOfParadise",
		"count" : 1
	},
	{
		"_id" : "XavierGarcia",
		"count" : 1
	},
	{
		"_id" : "Paul Tetreault",
		"count" : 1
	},
	{
		"_id" : "DLichti",
		"count" : 1
	},
	{
		"_id" : "acole_0157",
		"count" : 1
	},
	{
		"_id" : "thomguertin",
		"count" : 1
	},
	{
		"_id" : "Jay11",
		"count" : 1
	},
	{
		"_id" : "ianlopez1115",
		"count" : 1
	},
	{
		"_id" : "KR-KRKR-KR",
		"count" : 1
	},
	{
		"_id" : "marisacalise",
		"count" : 1
	},
	{
		"_id" : "kylealbert",
		"count" : 1
	},
	{
		"_id" : "dgitto",
		"count" : 1
	},
	{
		"_id" : "DavidS-Faber",
		"count" : 1
	},
	{
		"_id" : "makalvy",
		"count" : 1
	},
	{
		"_id" : "MikePosch",
		"count" : 1
	},
	{
		"_id" : "burmanarchitects",
		"count" : 1
	},
	{
		"_id" : "elkueb",
		"count" : 1
	},
	{
		"_id" : "hobbesvsboyle",
		"count" : 1
	},
	{
		"_id" : "geodreieck4711",
		"count" : 1
	},
	{
		"_id" : "paintdrops",
		"count" : 1
	},
	{
		"_id" : "Gutsycat",
		"count" : 1
	},
	{
		"_id" : "geozeisig",
		"count" : 1
	},
	{
		"_id" : "lminassian",
		"count" : 1
	},
	{
		"_id" : "BuganiniQ",
		"count" : 1
	},
	{
		"_id" : "Spanholz",
		"count" : 1
	},
	{
		"_id" : "ordinarylegends",
		"count" : 1
	},
	{
		"_id" : "Dami_Tn",
		"count" : 1
	},
	{
		"_id" : "mapper999",
		"count" : 1
	},
	{
		"_id" : "Thomas Haley",
		"count" : 1
	},
	{
		"_id" : "PA94",
		"count" : 1
	},
	{
		"_id" : "baysidenurs",
		"count" : 1
	},
	{
		"_id" : "philgasbarros",
		"count" : 1
	},
	{
		"_id" : "Phil Scherer",
		"count" : 1
	},
	{
		"_id" : "jrtmcgee",
		"count" : 1
	},
	{
		"_id" : "ethylisocyanat",
		"count" : 1
	},
	{
		"_id" : "IanH",
		"count" : 1
	},
	{
		"_id" : "wandsecacher",
		"count" : 1
	},
	{
		"_id" : "mBro",
		"count" : 1
	},
	{
		"_id" : "Cheyanna",
		"count" : 1
	},
	{
		"_id" : "dforsi",
		"count" : 1
	},
	{
		"_id" : "sabas88",
		"count" : 1
	},
	{
		"_id" : "Gabriel Yoran",
		"count" : 1
	},
	{
		"_id" : "highflyer74",
		"count" : 1
	},
	{
		"_id" : "jalrnc",
		"count" : 1
	},
	{
		"_id" : "MalcolmDrenttel",
		"count" : 1
	},
	{
		"_id" : "Claudius Henrichs",
		"count" : 1
	},
	{
		"_id" : "Statler75",
		"count" : 1
	},
	{
		"_id" : "jayabs24",
		"count" : 1
	},
	{
		"_id" : "michaelcaplan",
		"count" : 1
	},
	{
		"_id" : "Phil Shipley",
		"count" : 1
	},
	{
		"_id" : "Manu1400",
		"count" : 1
	},
	{
		"_id" : "ksharma198",
		"count" : 1
	},
	{
		"_id" : "mdroads",
		"count" : 1
	},
	{
		"_id" : "Michael Adis",
		"count" : 1
	},
	{
		"_id" : "tbmow",
		"count" : 1
	},
	{
		"_id" : "Jochen Topf",
		"count" : 1
	},
	{
		"_id" : "richmondrental",
		"count" : 1
	},
	{
		"_id" : "kenpoole",
		"count" : 1
	},
	{
		"_id" : "emacsen",
		"count" : 1
	},
	{
		"_id" : "Rafael Pazos",
		"count" : 1
	},
	{
		"_id" : "carterskemp",
		"count" : 1
	},
	{
		"_id" : "landfahrer",
		"count" : 1
	},
	{
		"_id" : "joesnr",
		"count" : 1
	},
	{
		"_id" : "muziriana",
		"count" : 1
	},
	{
		"_id" : "okilimu",
		"count" : 1
	},
	{
		"_id" : "FvGordon",
		"count" : 1
	},
	{
		"_id" : "Katie Lynne",
		"count" : 1
	}
]
